pbsparse/__init__.py
pbsparse/pbsparse.py
pbsparse-0.2.4.dist-info/licenses/LICENSE
test/records
test/test_filtering.py
test/test_processing.py
pbsparse-0.2.4.dist-info/METADATA
pbsparse-0.2.4.dist-info/WHEEL
pbsparse-0.2.4.dist-info/top_level.txt
pbsparse-0.2.4.dist-info/RECORD
