Metadata-Version: 2.4
Name: pbsparse
Version: 0.2.4
Summary: A package for processing PBS Pro accounting records
Author-email: Brian Vanderwende <vanderwb@ucar.edu>
License-Expression: MIT
Project-URL: homepage, https://github.com/NCAR/pbsparse
Project-URL: issues, https://github.com/NCAR/pbsparse/issues
Classifier: Programming Language :: Python :: 3
Classifier: Development Status :: 4 - Beta
Classifier: Operating System :: OS Independent
Classifier: Topic :: System :: Distributed Computing
Requires-Python: >=3.6
License-File: LICENSE
Dynamic: license-file
